{"date":"2025-09-06","updateTime":"15:17:48","list":[{"city":"北京","92h":"7.11","95h":"7.57","98h":"9.07","0h":"6.8"},{"city":"天津","92h":"7.1","95h":"7.51","98h":"9.01","0h":"6.75"},{"city":"上海","92h":"7.08","95h":"7.53","98h":"9.43","0h":"6.73"},{"city":"重庆","92h":"7.18","95h":"7.59","98h":"9.16","0h":"6.83"},{"city":"河北","92h":"7.1","95h":"7.51","98h":"8.33","0h":"6.75"},{"city":"山西","92h":"7.07","95h":"7.63","98h":"9.31","0h":"6.82"},{"city":"辽宁","92h":"7.21","95h":"7.7","98h":"8.4","0h":"6.66"},{"city":"吉林","92h":"7.08","95h":"7.63","98h":"8.32","0h":"6.68"},{"city":"黑龙江","92h":"7.08","95h":"7.58","98h":"8.6","0h":"6.57"},{"city":"江苏","92h":"7.09","95h":"7.54","98h":"9.58","0h":"6.72"},{"city":"浙江","92h":"7.09","95h":"7.54","98h":"9.04","0h":"6.74"},{"city":"安徽","92h":"7.08","95h":"7.58","98h":"9.08","0h":"6.79"},{"city":"福建","92h":"7.08","95h":"7.56","98h":"9.06","0h":"6.75"},{"city":"江西","92h":"7.08","95h":"7.6","98h":"9.1","0h":"6.8"},{"city":"山东","92h":"7.08","95h":"7.59","98h":"8.59","0h":"6.68"},{"city":"河南","92h":"7.12","95h":"7.6","98h":"8.55","0h":"6.74"},{"city":"湖北","92h":"7.12","95h":"7.62","98h":"9.56","0h":"6.75"},{"city":"湖南","92h":"7.07","95h":"7.51","98h":"8.71","0h":"6.82"},{"city":"广东","92h":"7.13","95h":"7.73","98h":"9.73","0h":"6.76"},{"city":"海南","92h":"8.23","95h":"8.74","98h":"9.88","0h":"6.84"},{"city":"四川","92h":"7.21","95h":"7.71","98h":"8.38","0h":"6.81"},{"city":"贵州","92h":"7.24","95h":"7.65","98h":"8.65","0h":"6.86"},{"city":"云南","92h":"7.26","95h":"7.79","98h":"8.47","0h":"6.83"},{"city":"陕西","92h":"7","95h":"7.4","98h":"9.72","0h":"6.66"},{"city":"甘肃","92h":"7.11","95h":"7.59","98h":"8.16","0h":"6.67"},{"city":"内蒙古","92h":"7.05","95h":"7.53","98h":"8.26","0h":"6.64"},{"city":"宁夏","92h":"7.02","95h":"7.42","98h":"8.48","0h":"6.65"},{"city":"新疆","92h":"6.89","95h":"7.38","98h":"8.24","0h":"6.52"},{"city":"广西","92h":"7.18","95h":"7.75","98h":"9","0h":"6.82"},{"city":"西藏","92h":"8","95h":"8.46","98h":"9.43","0h":"7.31"},{"city":"青海","92h":"7.07","95h":"7.58","98h":"8.26","0h":"6.69"}]}